flask_share/__init__.py
flask_share/static/css/share.min.css
flask_share/static/fonts/iconfont.eot
flask_share/static/fonts/iconfont.svg
flask_share/static/fonts/iconfont.ttf
flask_share/static/fonts/iconfont.woff
flask_share/static/js/jquery.share.min.js
flask_share/static/js/social-share.min.js
Flask_Jy_Share-0.1.0.dist-info/LICENSE
Flask_Jy_Share-0.1.0.dist-info/METADATA
Flask_Jy_Share-0.1.0.dist-info/WHEEL
Flask_Jy_Share-0.1.0.dist-info/top_level.txt
Flask_Jy_Share-0.1.0.dist-info/RECORD
